{
  "lastUpdated": "2026-02-20",
  "stats": {
    "totalAristocrats": 68,
    "avgYield": 2.7,
    "avg10YearGrowth": 7.4,
    "avgPayoutRatio": 51
  },
  "sectors": [
    { "name": "Consumer Staples", "count": 15, "icon": "fa-shopping-basket" },
    { "name": "Industrials", "count": 13, "icon": "fa-industry" },
    { "name": "Healthcare", "count": 10, "icon": "fa-heartbeat" },
    { "name": "Financials", "count": 9, "icon": "fa-university" },
    { "name": "Materials", "count": 8, "icon": "fa-gem" },
    { "name": "Utilities", "count": 6, "icon": "fa-bolt" },
    { "name": "Real Estate", "count": 4, "icon": "fa-building" },
    { "name": "Consumer Discretionary", "count": 2, "icon": "fa-car" },
    { "name": "Energy", "count": 1, "icon": "fa-gas-pump" }
  ],
  "aristocrats": [
    {
      "ticker": "AWR",
      "name": "American States Water",
      "yield": 2.35,
      "years": 70,
      "growth5Y": 8.5,
      "payoutRatio": 58,
      "sector": "Utilities",
      "sectorSlug": "utilities",
      "marketCap": "3.2B",
      "exDividendDate": "2026-02-14",
      "isKing": true
    },
    {
      "ticker": "DOV",
      "name": "Dover Corporation",
      "yield": 1.18,
      "years": 69,
      "growth5Y": 7.2,
      "payoutRatio": 28,
      "sector": "Industrials",
      "sectorSlug": "industrials",
      "marketCap": "25.8B",
      "exDividendDate": "2026-02-27",
      "isKing": true
    },
    {
      "ticker": "NWN",
      "name": "Northwest Natural Holding",
      "yield": 4.82,
      "years": 69,
      "growth5Y": 0.6,
      "payoutRatio": 78,
      "sector": "Utilities",
      "sectorSlug": "utilities",
      "marketCap": "1.5B",
      "exDividendDate": "2026-01-30",
      "isKing": true
    },
    {
      "ticker": "PG",
      "name": "Procter & Gamble",
      "yield": 2.42,
      "years": 68,
      "growth5Y": 6.1,
      "payoutRatio": 62,
      "sector": "Consumer Staples",
      "sectorSlug": "consumer-staples",
      "marketCap": "385B",
      "exDividendDate": "2026-01-23",
      "isKing": true
    },
    {
      "ticker": "GPC",
      "name": "Genuine Parts Company",
      "yield": 2.75,
      "years": 68,
      "growth5Y": 5.8,
      "payoutRatio": 52,
      "sector": "Consumer Discretionary",
      "sectorSlug": "consumer-discretionary",
      "marketCap": "18.5B",
      "exDividendDate": "2026-03-06",
      "isKing": true
    },
    {
      "ticker": "PH",
      "name": "Parker-Hannifin",
      "yield": 1.12,
      "years": 68,
      "growth5Y": 15.2,
      "payoutRatio": 22,
      "sector": "Industrials",
      "sectorSlug": "industrials",
      "marketCap": "82B",
      "exDividendDate": "2026-02-13",
      "isKing": true
    },
    {
      "ticker": "EMR",
      "name": "Emerson Electric",
      "yield": 1.85,
      "years": 67,
      "growth5Y": 1.5,
      "payoutRatio": 45,
      "sector": "Industrials",
      "sectorSlug": "industrials",
      "marketCap": "72B",
      "exDividendDate": "2026-02-14",
      "isKing": true
    },
    {
      "ticker": "MMM",
      "name": "3M Company",
      "yield": 5.82,
      "years": 66,
      "growth5Y": 0.8,
      "payoutRatio": 78,
      "sector": "Industrials",
      "sectorSlug": "industrials",
      "marketCap": "58B",
      "exDividendDate": "2026-02-20",
      "isKing": true
    },
    {
      "ticker": "CINF",
      "name": "Cincinnati Financial",
      "yield": 2.48,
      "years": 64,
      "growth5Y": 8.5,
      "payoutRatio": 32,
      "sector": "Financials",
      "sectorSlug": "financials",
      "marketCap": "21B",
      "exDividendDate": "2026-03-17",
      "isKing": true
    },
    {
      "ticker": "KO",
      "name": "Coca-Cola",
      "yield": 3.05,
      "years": 62,
      "growth5Y": 3.8,
      "payoutRatio": 67,
      "sector": "Consumer Staples",
      "sectorSlug": "consumer-staples",
      "marketCap": "268B",
      "exDividendDate": "2026-03-13",
      "isKing": true
    },
    {
      "ticker": "JNJ",
      "name": "Johnson & Johnson",
      "yield": 3.12,
      "years": 62,
      "growth5Y": 5.9,
      "payoutRatio": 44,
      "sector": "Healthcare",
      "sectorSlug": "healthcare",
      "marketCap": "365B",
      "exDividendDate": "2026-02-24",
      "isKing": true
    },
    {
      "ticker": "LOW",
      "name": "Lowe's Companies",
      "yield": 1.82,
      "years": 62,
      "growth5Y": 18.5,
      "payoutRatio": 35,
      "sector": "Consumer Discretionary",
      "sectorSlug": "consumer-discretionary",
      "marketCap": "142B",
      "exDividendDate": "2026-01-22",
      "isKing": true
    },
    {
      "ticker": "CL",
      "name": "Colgate-Palmolive",
      "yield": 2.18,
      "years": 61,
      "growth5Y": 3.2,
      "payoutRatio": 58,
      "sector": "Consumer Staples",
      "sectorSlug": "consumer-staples",
      "marketCap": "78B",
      "exDividendDate": "2026-01-22",
      "isKing": true
    },
    {
      "ticker": "HRL",
      "name": "Hormel Foods",
      "yield": 3.65,
      "years": 58,
      "growth5Y": 6.2,
      "payoutRatio": 62,
      "sector": "Consumer Staples",
      "sectorSlug": "consumer-staples",
      "marketCap": "17B",
      "exDividendDate": "2026-01-14",
      "isKing": true
    },
    {
      "ticker": "SWK",
      "name": "Stanley Black & Decker",
      "yield": 3.85,
      "years": 57,
      "growth5Y": 5.1,
      "payoutRatio": 82,
      "sector": "Industrials",
      "sectorSlug": "industrials",
      "marketCap": "14B",
      "exDividendDate": "2026-03-05",
      "isKing": true
    },
    {
      "ticker": "FRT",
      "name": "Federal Realty Investment Trust",
      "yield": 4.15,
      "years": 57,
      "growth5Y": 1.8,
      "payoutRatio": 68,
      "sector": "Real Estate",
      "sectorSlug": "real-estate",
      "marketCap": "9.2B",
      "exDividendDate": "2026-03-17",
      "isKing": true
    },
    {
      "ticker": "SYY",
      "name": "Sysco Corporation",
      "yield": 2.72,
      "years": 55,
      "growth5Y": 5.8,
      "payoutRatio": 52,
      "sector": "Consumer Staples",
      "sectorSlug": "consumer-staples",
      "marketCap": "38B",
      "exDividendDate": "2026-01-03",
      "isKing": true
    },
    {
      "ticker": "BDX",
      "name": "Becton Dickinson",
      "yield": 1.62,
      "years": 53,
      "growth5Y": 4.8,
      "payoutRatio": 32,
      "sector": "Healthcare",
      "sectorSlug": "healthcare",
      "marketCap": "68B",
      "exDividendDate": "2026-03-10",
      "isKing": true
    },
    {
      "ticker": "ABBV",
      "name": "AbbVie Inc",
      "yield": 3.52,
      "years": 52,
      "growth5Y": 8.2,
      "payoutRatio": 48,
      "sector": "Healthcare",
      "sectorSlug": "healthcare",
      "marketCap": "310B",
      "exDividendDate": "2026-01-14",
      "isKing": true
    },
    {
      "ticker": "PEP",
      "name": "PepsiCo",
      "yield": 2.95,
      "years": 52,
      "growth5Y": 7.1,
      "payoutRatio": 65,
      "sector": "Consumer Staples",
      "sectorSlug": "consumer-staples",
      "marketCap": "228B",
      "exDividendDate": "2026-03-06",
      "isKing": true
    },
    {
      "ticker": "PPG",
      "name": "PPG Industries",
      "yield": 1.92,
      "years": 52,
      "growth5Y": 6.5,
      "payoutRatio": 38,
      "sector": "Materials",
      "sectorSlug": "materials",
      "marketCap": "28B",
      "exDividendDate": "2026-02-20",
      "isKing": true
    },
    {
      "ticker": "WMT",
      "name": "Walmart Inc",
      "yield": 1.32,
      "years": 51,
      "growth5Y": 1.9,
      "payoutRatio": 35,
      "sector": "Consumer Staples",
      "sectorSlug": "consumer-staples",
      "marketCap": "542B",
      "exDividendDate": "2026-03-14",
      "isKing": true
    },
    {
      "ticker": "TGT",
      "name": "Target Corporation",
      "yield": 2.95,
      "years": 51,
      "growth5Y": 11.2,
      "payoutRatio": 48,
      "sector": "Consumer Staples",
      "sectorSlug": "consumer-staples",
      "marketCap": "62B",
      "exDividendDate": "2026-02-18",
      "isKing": true
    },
    {
      "ticker": "ABT",
      "name": "Abbott Laboratories",
      "yield": 1.85,
      "years": 51,
      "growth5Y": 12.8,
      "payoutRatio": 42,
      "sector": "Healthcare",
      "sectorSlug": "healthcare",
      "marketCap": "198B",
      "exDividendDate": "2026-01-14",
      "isKing": true
    },
    {
      "ticker": "NUE",
      "name": "Nucor Corporation",
      "yield": 1.45,
      "years": 51,
      "growth5Y": 23.5,
      "payoutRatio": 18,
      "sector": "Materials",
      "sectorSlug": "materials",
      "marketCap": "36B",
      "exDividendDate": "2026-03-28",
      "isKing": true
    },
    {
      "ticker": "ITW",
      "name": "Illinois Tool Works",
      "yield": 2.15,
      "years": 50,
      "growth5Y": 7.2,
      "payoutRatio": 52,
      "sector": "Industrials",
      "sectorSlug": "industrials",
      "marketCap": "75B",
      "exDividendDate": "2026-03-27",
      "isKing": true
    },
    {
      "ticker": "CVX",
      "name": "Chevron Corporation",
      "yield": 4.25,
      "years": 37,
      "growth5Y": 6.2,
      "payoutRatio": 55,
      "sector": "Energy",
      "sectorSlug": "energy",
      "marketCap": "275B",
      "exDividendDate": "2026-02-14",
      "isKing": false
    },
    {
      "ticker": "XOM",
      "name": "Exxon Mobil",
      "yield": 3.42,
      "years": 42,
      "growth5Y": 3.1,
      "payoutRatio": 42,
      "sector": "Energy",
      "sectorSlug": "energy",
      "marketCap": "485B",
      "exDividendDate": "2026-02-12",
      "isKing": false
    },
    {
      "ticker": "MCD",
      "name": "McDonald's Corporation",
      "yield": 2.25,
      "years": 48,
      "growth5Y": 8.1,
      "payoutRatio": 55,
      "sector": "Consumer Discretionary",
      "sectorSlug": "consumer-discretionary",
      "marketCap": "215B",
      "exDividendDate": "2026-02-28",
      "isKing": false
    },
    {
      "ticker": "ADP",
      "name": "Automatic Data Processing",
      "yield": 2.05,
      "years": 49,
      "growth5Y": 12.5,
      "payoutRatio": 58,
      "sector": "Industrials",
      "sectorSlug": "industrials",
      "marketCap": "115B",
      "exDividendDate": "2026-03-13",
      "isKing": false
    },
    {
      "ticker": "MDT",
      "name": "Medtronic",
      "yield": 3.25,
      "years": 47,
      "growth5Y": 7.8,
      "payoutRatio": 52,
      "sector": "Healthcare",
      "sectorSlug": "healthcare",
      "marketCap": "108B",
      "exDividendDate": "2026-03-20",
      "isKing": false
    },
    {
      "ticker": "AFL",
      "name": "Aflac Inc",
      "yield": 2.08,
      "years": 42,
      "growth5Y": 15.2,
      "payoutRatio": 28,
      "sector": "Financials",
      "sectorSlug": "financials",
      "marketCap": "52B",
      "exDividendDate": "2026-02-18",
      "isKing": false
    },
    {
      "ticker": "TROW",
      "name": "T. Rowe Price",
      "yield": 4.35,
      "years": 38,
      "growth5Y": 12.8,
      "payoutRatio": 45,
      "sector": "Financials",
      "sectorSlug": "financials",
      "marketCap": "25B",
      "exDividendDate": "2026-03-14",
      "isKing": false
    },
    {
      "ticker": "BEN",
      "name": "Franklin Resources",
      "yield": 5.85,
      "years": 44,
      "growth5Y": 4.2,
      "payoutRatio": 68,
      "sector": "Financials",
      "sectorSlug": "financials",
      "marketCap": "12B",
      "exDividendDate": "2026-03-28",
      "isKing": false
    },
    {
      "ticker": "SPGI",
      "name": "S&P Global",
      "yield": 0.78,
      "years": 50,
      "growth5Y": 14.5,
      "payoutRatio": 25,
      "sector": "Financials",
      "sectorSlug": "financials",
      "marketCap": "145B",
      "exDividendDate": "2026-02-25",
      "isKing": true
    },
    {
      "ticker": "CB",
      "name": "Chubb Limited",
      "yield": 1.35,
      "years": 31,
      "growth5Y": 4.8,
      "payoutRatio": 22,
      "sector": "Financials",
      "sectorSlug": "financials",
      "marketCap": "112B",
      "exDividendDate": "2026-03-19",
      "isKing": false
    },
    {
      "ticker": "O",
      "name": "Realty Income",
      "yield": 5.65,
      "years": 29,
      "growth5Y": 3.1,
      "payoutRatio": 75,
      "sector": "Real Estate",
      "sectorSlug": "real-estate",
      "marketCap": "48B",
      "exDividendDate": "2026-02-28",
      "isKing": false
    },
    {
      "ticker": "ESS",
      "name": "Essex Property Trust",
      "yield": 3.62,
      "years": 30,
      "growth5Y": 4.2,
      "payoutRatio": 68,
      "sector": "Real Estate",
      "sectorSlug": "real-estate",
      "marketCap": "18B",
      "exDividendDate": "2026-03-28",
      "isKing": false
    },
    {
      "ticker": "CAT",
      "name": "Caterpillar Inc",
      "yield": 1.58,
      "years": 30,
      "growth5Y": 8.2,
      "payoutRatio": 25,
      "sector": "Industrials",
      "sectorSlug": "industrials",
      "marketCap": "175B",
      "exDividendDate": "2026-01-20",
      "isKing": false
    },
    {
      "ticker": "GD",
      "name": "General Dynamics",
      "yield": 2.12,
      "years": 32,
      "growth5Y": 7.5,
      "payoutRatio": 38,
      "sector": "Industrials",
      "sectorSlug": "industrials",
      "marketCap": "78B",
      "exDividendDate": "2026-01-10",
      "isKing": false
    },
    {
      "ticker": "APD",
      "name": "Air Products & Chemicals",
      "yield": 2.55,
      "years": 42,
      "growth5Y": 9.8,
      "payoutRatio": 62,
      "sector": "Materials",
      "sectorSlug": "materials",
      "marketCap": "62B",
      "exDividendDate": "2026-03-28",
      "isKing": false
    },
    {
      "ticker": "SHW",
      "name": "Sherwin-Williams",
      "yield": 0.85,
      "years": 46,
      "growth5Y": 15.2,
      "payoutRatio": 28,
      "sector": "Materials",
      "sectorSlug": "materials",
      "marketCap": "85B",
      "exDividendDate": "2026-02-21",
      "isKing": false
    },
    {
      "ticker": "ECL",
      "name": "Ecolab Inc",
      "yield": 1.12,
      "years": 32,
      "growth5Y": 6.5,
      "payoutRatio": 35,
      "sector": "Materials",
      "sectorSlug": "materials",
      "marketCap": "62B",
      "exDividendDate": "2026-03-17",
      "isKing": false
    },
    {
      "ticker": "LIN",
      "name": "Linde plc",
      "yield": 1.22,
      "years": 31,
      "growth5Y": 8.5,
      "payoutRatio": 42,
      "sector": "Materials",
      "sectorSlug": "materials",
      "marketCap": "215B",
      "exDividendDate": "2026-03-05",
      "isKing": false
    },
    {
      "ticker": "CLX",
      "name": "Clorox Company",
      "yield": 3.42,
      "years": 46,
      "growth5Y": 5.2,
      "payoutRatio": 72,
      "sector": "Consumer Staples",
      "sectorSlug": "consumer-staples",
      "marketCap": "18B",
      "exDividendDate": "2026-01-28",
      "isKing": false
    },
    {
      "ticker": "KMB",
      "name": "Kimberly-Clark",
      "yield": 3.55,
      "years": 52,
      "growth5Y": 3.8,
      "payoutRatio": 65,
      "sector": "Consumer Staples",
      "sectorSlug": "consumer-staples",
      "marketCap": "45B",
      "exDividendDate": "2026-03-06",
      "isKing": true
    },
    {
      "ticker": "ED",
      "name": "Consolidated Edison",
      "yield": 3.48,
      "years": 50,
      "growth5Y": 2.5,
      "payoutRatio": 68,
      "sector": "Utilities",
      "sectorSlug": "utilities",
      "marketCap": "32B",
      "exDividendDate": "2026-02-12",
      "isKing": true
    },
    {
      "ticker": "ATO",
      "name": "Atmos Energy",
      "yield": 2.58,
      "years": 40,
      "growth5Y": 8.5,
      "payoutRatio": 48,
      "sector": "Utilities",
      "sectorSlug": "utilities",
      "marketCap": "20B",
      "exDividendDate": "2026-02-19",
      "isKing": false
    },
    {
      "ticker": "WBA",
      "name": "Walgreens Boots Alliance",
      "yield": 8.25,
      "years": 48,
      "growth5Y": 2.1,
      "payoutRatio": 85,
      "sector": "Consumer Staples",
      "sectorSlug": "consumer-staples",
      "marketCap": "12B",
      "exDividendDate": "2026-02-18",
      "isKing": false
    }
  ]
}
