{
  "lastUpdated": "2026-04-29T17:36:21Z",
  "picks": [
    {
      "symbol": "NVDA",
      "name": "NVIDIA Corporation",
      "signal": "HOLD",
      "currentPrice": 209.3,
      "potentialGain": 12.0
    },
    {
      "symbol": "MSFT",
      "name": "Microsoft Corporation",
      "signal": "BUY",
      "currentPrice": 423.3,
      "potentialGain": 12.0
    },
    {
      "symbol": "AMZN",
      "name": "Amazon.com Inc.",
      "signal": "BUY",
      "currentPrice": 262.12,
      "potentialGain": 12.0
    },
    {
      "symbol": "GOOGL",
      "name": "Alphabet Inc.",
      "signal": "BUY",
      "currentPrice": 348.88,
      "potentialGain": 12.0
    },
    {
      "symbol": "TSLA",
      "name": "Tesla Inc.",
      "signal": "HOLD",
      "currentPrice": 373.09,
      "potentialGain": 12.0
    }
  ]
}